casestyles/__init__.py
casestyles-1.2.3.dist-info/METADATA
casestyles-1.2.3.dist-info/WHEEL
casestyles-1.2.3.dist-info/top_level.txt
casestyles-1.2.3.dist-info/RECORD
