Metadata-Version: 2.1
Name: casestyles
Version: 1.2.3
Summary: A package for converting case styles to each other
Home-page: https://github.com/Chebotarev-Alexey/CaseStyles
Author: Alexey-Chebotarev
Classifier: Programming Language :: Python :: 3
Classifier: License :: OSI Approved :: MIT License
Classifier: Operating System :: OS Independent
Requires-Python: >=3.6
